{"title":"Python-文件操作","slug":"Python-文件操作","date":"2020-04-29T10:12:39.000Z","updated":"2020-04-29T10:12:54.987Z","comments":true,"path":"api/articles/Python-文件操作.json","excerpt":null,"covers":null,"content":"<!-- build time:Wed Apr 29 2020 18:13:23 GMT+0800 (GMT+08:00) --><!-- rebuild by neat -->","more":"<!-- build time:Wed Apr 29 2020 18:13:23 GMT+0800 (GMT+08:00) --><!-- rebuild by neat -->","categories":[{"name":"计算机基础","path":"api/categories/计算机基础.json"},{"name":"Python","path":"api/categories/Python.json"}],"tags":[{"name":"Python","path":"api/tags/Python.json"}]}