{"title":"备忘录模式","slug":"备忘录模式","date":"2020-05-14T15:25:06.000Z","updated":"2020-05-14T15:28:37.763Z","comments":true,"path":"api/articles/备忘录模式.json","excerpt":null,"covers":null,"content":"<!-- build time:Thu May 14 2020 23:38:44 GMT+0800 (GMT+08:00) --><h1 id=\"定义与特点\"><a class=\"markdownIt-Anchor\" href=\"#定义与特点\"></a> 定义与特点</h1><p>备忘录（Memento）模式的定义：在不破坏封装性的前提下，捕获一个对象的内部状态，并在该对象之外保存这个状态，以便以后当需要时能将该对象恢复到原先保存的状态。该模式又叫快照模式。备忘录模式是一种对象行为型模式，其主要优点如下。</p><ul><li>提供了一种可以恢复状态的机制。当用户需要时能够比较方便地将数据恢复到某个历史的状态。</li><li>实现了内部状态的封装。除了创建它的发起人之外，其他对象都不能够访问这些状态信息。</li><li>简化了发起人类。发起人不需要管理和保存其内部状态的各个备份，所有状态信息都保存在备忘录中，并由管理者进行管理，这符合单一职责原则。</li></ul><p>其主要缺点是：资源消耗大。如果要保存的内部状态信息过多或者特别频繁，将会占用比较大的内存资源。</p><h1 id=\"结构与实现\"><a class=\"markdownIt-Anchor\" href=\"#结构与实现\"></a> 结构与实现</h1><p>备忘录模式的核心是设计备忘录类以及用于管理备忘录的管理者类，主要角色如下：</p><ul><li>发起人（Originator）角色：记录当前时刻的内部状态信息，提供创建备忘录和恢复备忘录数据的功能，实现其他业务功能，它可以访问备忘录里的所有信息。</li><li>备忘录（Memento）角色：负责存储发起人的内部状态，在需要的时候提供这些内部状态给发起人。</li><li>管理者（Caretaker）角色：对备忘录进行管理，提供保存与获取备忘录的功能，但其不能对备忘录的内容进行访问与修改。</li></ul><h2 id=\"实现\"><a class=\"markdownIt-Anchor\" href=\"#实现\"></a> 实现</h2><p>备忘录模式的代码实现如下：</p><figure class=\"highlight java\"><table><tr><td class=\"gutter\"><pre><span class=\"line\">1</span><br><span class=\"line\">2</span><br><span class=\"line\">3</span><br><span class=\"line\">4</span><br><span class=\"line\">5</span><br><span class=\"line\">6</span><br><span class=\"line\">7</span><br><span class=\"line\">8</span><br><span class=\"line\">9</span><br><span class=\"line\">10</span><br><span class=\"line\">11</span><br><span class=\"line\">12</span><br><span class=\"line\">13</span><br><span class=\"line\">14</span><br><span class=\"line\">15</span><br><span class=\"line\">16</span><br><span class=\"line\">17</span><br><span class=\"line\">18</span><br><span class=\"line\">19</span><br><span class=\"line\">20</span><br><span class=\"line\">21</span><br><span class=\"line\">22</span><br><span class=\"line\">23</span><br><span class=\"line\">24</span><br><span class=\"line\">25</span><br><span class=\"line\">26</span><br><span class=\"line\">27</span><br><span class=\"line\">28</span><br><span class=\"line\">29</span><br><span class=\"line\">30</span><br><span class=\"line\">31</span><br><span class=\"line\">32</span><br><span class=\"line\">33</span><br><span class=\"line\">34</span><br><span class=\"line\">35</span><br><span class=\"line\">36</span><br><span class=\"line\">37</span><br><span class=\"line\">38</span><br><span class=\"line\">39</span><br><span class=\"line\">40</span><br><span class=\"line\">41</span><br><span class=\"line\">42</span><br><span class=\"line\">43</span><br><span class=\"line\">44</span><br><span class=\"line\">45</span><br><span class=\"line\">46</span><br><span class=\"line\">47</span><br><span class=\"line\">48</span><br><span class=\"line\">49</span><br><span class=\"line\">50</span><br><span class=\"line\">51</span><br><span class=\"line\">52</span><br><span class=\"line\">53</span><br><span class=\"line\">54</span><br><span class=\"line\">55</span><br><span class=\"line\">56</span><br><span class=\"line\">57</span><br><span class=\"line\">58</span><br><span class=\"line\">59</span><br><span class=\"line\">60</span><br><span class=\"line\">61</span><br><span class=\"line\">62</span><br><span class=\"line\">63</span><br><span class=\"line\">64</span><br><span class=\"line\">65</span><br><span class=\"line\">66</span><br><span class=\"line\">67</span><br><span class=\"line\">68</span><br><span class=\"line\">69</span><br><span class=\"line\">70</span><br><span class=\"line\">71</span><br><span class=\"line\">72</span><br></pre></td><td class=\"code\"><pre><span class=\"line\"><span class=\"keyword\">package</span> memento;</span><br><span class=\"line\"><span class=\"keyword\">public</span> <span class=\"class\"><span class=\"keyword\">class</span> <span class=\"title\">MementoPattern</span></span></span><br><span class=\"line\"><span class=\"class\"></span>&#123;</span><br><span class=\"line\">    <span class=\"function\"><span class=\"keyword\">public</span> <span class=\"keyword\">static</span> <span class=\"keyword\">void</span> <span class=\"title\">main</span><span class=\"params\">(String[] args)</span></span></span><br><span class=\"line\"><span class=\"function\">    </span>&#123;</span><br><span class=\"line\">        Originator or=<span class=\"keyword\">new</span> Originator();</span><br><span class=\"line\">        Caretaker cr=<span class=\"keyword\">new</span> Caretaker();       </span><br><span class=\"line\">        or.setState(<span class=\"string\">\"S0\"</span>); </span><br><span class=\"line\">        System.out.println(<span class=\"string\">\"初始状态:\"</span>+or.getState());           </span><br><span class=\"line\">        cr.setMemento(or.createMemento()); <span class=\"comment\">//保存状态      </span></span><br><span class=\"line\">        or.setState(<span class=\"string\">\"S1\"</span>); </span><br><span class=\"line\">        System.out.println(<span class=\"string\">\"新的状态:\"</span>+or.getState());        </span><br><span class=\"line\">        or.restoreMemento(cr.getMemento()); <span class=\"comment\">//恢复状态</span></span><br><span class=\"line\">        System.out.println(<span class=\"string\">\"恢复状态:\"</span>+or.getState());</span><br><span class=\"line\">    &#125;</span><br><span class=\"line\">&#125;</span><br><span class=\"line\"><span class=\"comment\">//备忘录</span></span><br><span class=\"line\"><span class=\"class\"><span class=\"keyword\">class</span> <span class=\"title\">Memento</span></span></span><br><span class=\"line\"><span class=\"class\"></span>&#123; </span><br><span class=\"line\">    <span class=\"keyword\">private</span> String state; </span><br><span class=\"line\">    <span class=\"function\"><span class=\"keyword\">public</span> <span class=\"title\">Memento</span><span class=\"params\">(String state)</span></span></span><br><span class=\"line\"><span class=\"function\">    </span>&#123; </span><br><span class=\"line\">        <span class=\"keyword\">this</span>.state=state; </span><br><span class=\"line\">    &#125;     </span><br><span class=\"line\">    <span class=\"function\"><span class=\"keyword\">public</span> <span class=\"keyword\">void</span> <span class=\"title\">setState</span><span class=\"params\">(String state)</span></span></span><br><span class=\"line\"><span class=\"function\">    </span>&#123; </span><br><span class=\"line\">        <span class=\"keyword\">this</span>.state=state; </span><br><span class=\"line\">    &#125;</span><br><span class=\"line\">    <span class=\"function\"><span class=\"keyword\">public</span> String <span class=\"title\">getState</span><span class=\"params\">()</span></span></span><br><span class=\"line\"><span class=\"function\">    </span>&#123; </span><br><span class=\"line\">        <span class=\"keyword\">return</span> state; </span><br><span class=\"line\">    &#125;</span><br><span class=\"line\">&#125;</span><br><span class=\"line\"><span class=\"comment\">//发起人</span></span><br><span class=\"line\"><span class=\"class\"><span class=\"keyword\">class</span> <span class=\"title\">Originator</span></span></span><br><span class=\"line\"><span class=\"class\"></span>&#123; </span><br><span class=\"line\">    <span class=\"keyword\">private</span> String state;     </span><br><span class=\"line\">    <span class=\"function\"><span class=\"keyword\">public</span> <span class=\"keyword\">void</span> <span class=\"title\">setState</span><span class=\"params\">(String state)</span></span></span><br><span class=\"line\"><span class=\"function\">    </span>&#123; </span><br><span class=\"line\">        <span class=\"keyword\">this</span>.state=state; </span><br><span class=\"line\">    &#125;</span><br><span class=\"line\">    <span class=\"function\"><span class=\"keyword\">public</span> String <span class=\"title\">getState</span><span class=\"params\">()</span></span></span><br><span class=\"line\"><span class=\"function\">    </span>&#123; </span><br><span class=\"line\">        <span class=\"keyword\">return</span> state; </span><br><span class=\"line\">    &#125;</span><br><span class=\"line\">    <span class=\"function\"><span class=\"keyword\">public</span> Memento <span class=\"title\">createMemento</span><span class=\"params\">()</span></span></span><br><span class=\"line\"><span class=\"function\">    </span>&#123; </span><br><span class=\"line\">        <span class=\"keyword\">return</span> <span class=\"keyword\">new</span> Memento(state); </span><br><span class=\"line\">    &#125; </span><br><span class=\"line\">    <span class=\"function\"><span class=\"keyword\">public</span> <span class=\"keyword\">void</span> <span class=\"title\">restoreMemento</span><span class=\"params\">(Memento m)</span></span></span><br><span class=\"line\"><span class=\"function\">    </span>&#123; </span><br><span class=\"line\">        <span class=\"keyword\">this</span>.setState(m.getState()); </span><br><span class=\"line\">    &#125; </span><br><span class=\"line\">&#125;</span><br><span class=\"line\"><span class=\"comment\">//管理者</span></span><br><span class=\"line\"><span class=\"class\"><span class=\"keyword\">class</span> <span class=\"title\">Caretaker</span></span></span><br><span class=\"line\"><span class=\"class\"></span>&#123; </span><br><span class=\"line\">    <span class=\"keyword\">private</span> Memento memento;       </span><br><span class=\"line\">    <span class=\"function\"><span class=\"keyword\">public</span> <span class=\"keyword\">void</span> <span class=\"title\">setMemento</span><span class=\"params\">(Memento m)</span></span></span><br><span class=\"line\"><span class=\"function\">    </span>&#123; </span><br><span class=\"line\">        memento=m; </span><br><span class=\"line\">    &#125;</span><br><span class=\"line\">    <span class=\"function\"><span class=\"keyword\">public</span> Memento <span class=\"title\">getMemento</span><span class=\"params\">()</span></span></span><br><span class=\"line\"><span class=\"function\">    </span>&#123; </span><br><span class=\"line\">        <span class=\"keyword\">return</span> memento; </span><br><span class=\"line\">    &#125;</span><br><span class=\"line\">&#125;</span><br><span class=\"line\"><span class=\"comment\">/*</span></span><br><span class=\"line\"><span class=\"comment\">*初始状态:S0</span></span><br><span class=\"line\"><span class=\"comment\">新的状态:S1</span></span><br><span class=\"line\"><span class=\"comment\">恢复状态:S0</span></span><br><span class=\"line\"><span class=\"comment\">*/</span></span><br></pre></td></tr></table></figure><h1 id=\"应用场景\"><a class=\"markdownIt-Anchor\" href=\"#应用场景\"></a> 应用场景</h1><ul><li>需要保存与恢复数据的场景，如玩游戏时的中间结果的存档功能。</li><li>需要提供一个可回滚操作的场景，如 Word、记事本、Photoshop，Eclipse 等软件在编辑时按 Ctrl+Z 组合键，还有数据库中事务操作。</li></ul><!-- rebuild by neat -->","more":"<!-- build time:Thu May 14 2020 23:38:44 GMT+0800 (GMT+08:00) --><h1 id=\"定义与特点\"><a class=\"markdownIt-Anchor\" href=\"#定义与特点\"></a> 定义与特点</h1><p>备忘录（Memento）模式的定义：在不破坏封装性的前提下，捕获一个对象的内部状态，并在该对象之外保存这个状态，以便以后当需要时能将该对象恢复到原先保存的状态。该模式又叫快照模式。备忘录模式是一种对象行为型模式，其主要优点如下。</p><ul><li>提供了一种可以恢复状态的机制。当用户需要时能够比较方便地将数据恢复到某个历史的状态。</li><li>实现了内部状态的封装。除了创建它的发起人之外，其他对象都不能够访问这些状态信息。</li><li>简化了发起人类。发起人不需要管理和保存其内部状态的各个备份，所有状态信息都保存在备忘录中，并由管理者进行管理，这符合单一职责原则。</li></ul><p>其主要缺点是：资源消耗大。如果要保存的内部状态信息过多或者特别频繁，将会占用比较大的内存资源。</p><h1 id=\"结构与实现\"><a class=\"markdownIt-Anchor\" href=\"#结构与实现\"></a> 结构与实现</h1><p>备忘录模式的核心是设计备忘录类以及用于管理备忘录的管理者类，主要角色如下：</p><ul><li>发起人（Originator）角色：记录当前时刻的内部状态信息，提供创建备忘录和恢复备忘录数据的功能，实现其他业务功能，它可以访问备忘录里的所有信息。</li><li>备忘录（Memento）角色：负责存储发起人的内部状态，在需要的时候提供这些内部状态给发起人。</li><li>管理者（Caretaker）角色：对备忘录进行管理，提供保存与获取备忘录的功能，但其不能对备忘录的内容进行访问与修改。</li></ul><h2 id=\"实现\"><a class=\"markdownIt-Anchor\" href=\"#实现\"></a> 实现</h2><p>备忘录模式的代码实现如下：</p><figure class=\"highlight java\"><table><tr><td class=\"gutter\"><pre><span class=\"line\">1</span><br><span class=\"line\">2</span><br><span class=\"line\">3</span><br><span class=\"line\">4</span><br><span class=\"line\">5</span><br><span class=\"line\">6</span><br><span class=\"line\">7</span><br><span class=\"line\">8</span><br><span class=\"line\">9</span><br><span class=\"line\">10</span><br><span class=\"line\">11</span><br><span class=\"line\">12</span><br><span class=\"line\">13</span><br><span class=\"line\">14</span><br><span class=\"line\">15</span><br><span class=\"line\">16</span><br><span class=\"line\">17</span><br><span class=\"line\">18</span><br><span class=\"line\">19</span><br><span class=\"line\">20</span><br><span class=\"line\">21</span><br><span class=\"line\">22</span><br><span class=\"line\">23</span><br><span class=\"line\">24</span><br><span class=\"line\">25</span><br><span class=\"line\">26</span><br><span class=\"line\">27</span><br><span class=\"line\">28</span><br><span class=\"line\">29</span><br><span class=\"line\">30</span><br><span class=\"line\">31</span><br><span class=\"line\">32</span><br><span class=\"line\">33</span><br><span class=\"line\">34</span><br><span class=\"line\">35</span><br><span class=\"line\">36</span><br><span class=\"line\">37</span><br><span class=\"line\">38</span><br><span class=\"line\">39</span><br><span class=\"line\">40</span><br><span class=\"line\">41</span><br><span class=\"line\">42</span><br><span class=\"line\">43</span><br><span class=\"line\">44</span><br><span class=\"line\">45</span><br><span class=\"line\">46</span><br><span class=\"line\">47</span><br><span class=\"line\">48</span><br><span class=\"line\">49</span><br><span class=\"line\">50</span><br><span class=\"line\">51</span><br><span class=\"line\">52</span><br><span class=\"line\">53</span><br><span class=\"line\">54</span><br><span class=\"line\">55</span><br><span class=\"line\">56</span><br><span class=\"line\">57</span><br><span class=\"line\">58</span><br><span class=\"line\">59</span><br><span class=\"line\">60</span><br><span class=\"line\">61</span><br><span class=\"line\">62</span><br><span class=\"line\">63</span><br><span class=\"line\">64</span><br><span class=\"line\">65</span><br><span class=\"line\">66</span><br><span class=\"line\">67</span><br><span class=\"line\">68</span><br><span class=\"line\">69</span><br><span class=\"line\">70</span><br><span class=\"line\">71</span><br><span class=\"line\">72</span><br></pre></td><td class=\"code\"><pre><span class=\"line\"><span class=\"keyword\">package</span> memento;</span><br><span class=\"line\"><span class=\"keyword\">public</span> <span class=\"class\"><span class=\"keyword\">class</span> <span class=\"title\">MementoPattern</span></span></span><br><span class=\"line\"><span class=\"class\"></span>&#123;</span><br><span class=\"line\">    <span class=\"function\"><span class=\"keyword\">public</span> <span class=\"keyword\">static</span> <span class=\"keyword\">void</span> <span class=\"title\">main</span><span class=\"params\">(String[] args)</span></span></span><br><span class=\"line\"><span class=\"function\">    </span>&#123;</span><br><span class=\"line\">        Originator or=<span class=\"keyword\">new</span> Originator();</span><br><span class=\"line\">        Caretaker cr=<span class=\"keyword\">new</span> Caretaker();       </span><br><span class=\"line\">        or.setState(<span class=\"string\">\"S0\"</span>); </span><br><span class=\"line\">        System.out.println(<span class=\"string\">\"初始状态:\"</span>+or.getState());           </span><br><span class=\"line\">        cr.setMemento(or.createMemento()); <span class=\"comment\">//保存状态      </span></span><br><span class=\"line\">        or.setState(<span class=\"string\">\"S1\"</span>); </span><br><span class=\"line\">        System.out.println(<span class=\"string\">\"新的状态:\"</span>+or.getState());        </span><br><span class=\"line\">        or.restoreMemento(cr.getMemento()); <span class=\"comment\">//恢复状态</span></span><br><span class=\"line\">        System.out.println(<span class=\"string\">\"恢复状态:\"</span>+or.getState());</span><br><span class=\"line\">    &#125;</span><br><span class=\"line\">&#125;</span><br><span class=\"line\"><span class=\"comment\">//备忘录</span></span><br><span class=\"line\"><span class=\"class\"><span class=\"keyword\">class</span> <span class=\"title\">Memento</span></span></span><br><span class=\"line\"><span class=\"class\"></span>&#123; </span><br><span class=\"line\">    <span class=\"keyword\">private</span> String state; </span><br><span class=\"line\">    <span class=\"function\"><span class=\"keyword\">public</span> <span class=\"title\">Memento</span><span class=\"params\">(String state)</span></span></span><br><span class=\"line\"><span class=\"function\">    </span>&#123; </span><br><span class=\"line\">        <span class=\"keyword\">this</span>.state=state; </span><br><span class=\"line\">    &#125;     </span><br><span class=\"line\">    <span class=\"function\"><span class=\"keyword\">public</span> <span class=\"keyword\">void</span> <span class=\"title\">setState</span><span class=\"params\">(String state)</span></span></span><br><span class=\"line\"><span class=\"function\">    </span>&#123; </span><br><span class=\"line\">        <span class=\"keyword\">this</span>.state=state; </span><br><span class=\"line\">    &#125;</span><br><span class=\"line\">    <span class=\"function\"><span class=\"keyword\">public</span> String <span class=\"title\">getState</span><span class=\"params\">()</span></span></span><br><span class=\"line\"><span class=\"function\">    </span>&#123; </span><br><span class=\"line\">        <span class=\"keyword\">return</span> state; </span><br><span class=\"line\">    &#125;</span><br><span class=\"line\">&#125;</span><br><span class=\"line\"><span class=\"comment\">//发起人</span></span><br><span class=\"line\"><span class=\"class\"><span class=\"keyword\">class</span> <span class=\"title\">Originator</span></span></span><br><span class=\"line\"><span class=\"class\"></span>&#123; </span><br><span class=\"line\">    <span class=\"keyword\">private</span> String state;     </span><br><span class=\"line\">    <span class=\"function\"><span class=\"keyword\">public</span> <span class=\"keyword\">void</span> <span class=\"title\">setState</span><span class=\"params\">(String state)</span></span></span><br><span class=\"line\"><span class=\"function\">    </span>&#123; </span><br><span class=\"line\">        <span class=\"keyword\">this</span>.state=state; </span><br><span class=\"line\">    &#125;</span><br><span class=\"line\">    <span class=\"function\"><span class=\"keyword\">public</span> String <span class=\"title\">getState</span><span class=\"params\">()</span></span></span><br><span class=\"line\"><span class=\"function\">    </span>&#123; </span><br><span class=\"line\">        <span class=\"keyword\">return</span> state; </span><br><span class=\"line\">    &#125;</span><br><span class=\"line\">    <span class=\"function\"><span class=\"keyword\">public</span> Memento <span class=\"title\">createMemento</span><span class=\"params\">()</span></span></span><br><span class=\"line\"><span class=\"function\">    </span>&#123; </span><br><span class=\"line\">        <span class=\"keyword\">return</span> <span class=\"keyword\">new</span> Memento(state); </span><br><span class=\"line\">    &#125; </span><br><span class=\"line\">    <span class=\"function\"><span class=\"keyword\">public</span> <span class=\"keyword\">void</span> <span class=\"title\">restoreMemento</span><span class=\"params\">(Memento m)</span></span></span><br><span class=\"line\"><span class=\"function\">    </span>&#123; </span><br><span class=\"line\">        <span class=\"keyword\">this</span>.setState(m.getState()); </span><br><span class=\"line\">    &#125; </span><br><span class=\"line\">&#125;</span><br><span class=\"line\"><span class=\"comment\">//管理者</span></span><br><span class=\"line\"><span class=\"class\"><span class=\"keyword\">class</span> <span class=\"title\">Caretaker</span></span></span><br><span class=\"line\"><span class=\"class\"></span>&#123; </span><br><span class=\"line\">    <span class=\"keyword\">private</span> Memento memento;       </span><br><span class=\"line\">    <span class=\"function\"><span class=\"keyword\">public</span> <span class=\"keyword\">void</span> <span class=\"title\">setMemento</span><span class=\"params\">(Memento m)</span></span></span><br><span class=\"line\"><span class=\"function\">    </span>&#123; </span><br><span class=\"line\">        memento=m; </span><br><span class=\"line\">    &#125;</span><br><span class=\"line\">    <span class=\"function\"><span class=\"keyword\">public</span> Memento <span class=\"title\">getMemento</span><span class=\"params\">()</span></span></span><br><span class=\"line\"><span class=\"function\">    </span>&#123; </span><br><span class=\"line\">        <span class=\"keyword\">return</span> memento; </span><br><span class=\"line\">    &#125;</span><br><span class=\"line\">&#125;</span><br><span class=\"line\"><span class=\"comment\">/*</span></span><br><span class=\"line\"><span class=\"comment\">*初始状态:S0</span></span><br><span class=\"line\"><span class=\"comment\">新的状态:S1</span></span><br><span class=\"line\"><span class=\"comment\">恢复状态:S0</span></span><br><span class=\"line\"><span class=\"comment\">*/</span></span><br></pre></td></tr></table></figure><h1 id=\"应用场景\"><a class=\"markdownIt-Anchor\" href=\"#应用场景\"></a> 应用场景</h1><ul><li>需要保存与恢复数据的场景，如玩游戏时的中间结果的存档功能。</li><li>需要提供一个可回滚操作的场景，如 Word、记事本、Photoshop，Eclipse 等软件在编辑时按 Ctrl+Z 组合键，还有数据库中事务操作。</li></ul><!-- rebuild by neat -->","categories":[{"name":"设计模式","path":"api/categories/设计模式.json"}],"tags":[{"name":"设计模式","path":"api/tags/设计模式.json"}]}